odoo/addons/date_range_account/README.rst
odoo/addons/date_range_account/__init__.py
odoo/addons/date_range_account/__manifest__.py
odoo/addons/date_range_account/i18n/date_range_account.pot
odoo/addons/date_range_account/i18n/es.po
odoo/addons/date_range_account/i18n/fr.po
odoo/addons/date_range_account/i18n/it.po
odoo/addons/date_range_account/i18n/nl.po
odoo/addons/date_range_account/i18n/tr.po
odoo/addons/date_range_account/readme/CONTRIBUTORS.md
odoo/addons/date_range_account/readme/DESCRIPTION.md
odoo/addons/date_range_account/security/ir.model.access.csv
odoo/addons/date_range_account/static/description/icon.png
odoo/addons/date_range_account/static/description/index.html
odoo/addons/date_range_account/views/date_range.xml
odoo_addon_date_range_account-18.0.1.0.0.4.dist-info/METADATA
odoo_addon_date_range_account-18.0.1.0.0.4.dist-info/WHEEL
odoo_addon_date_range_account-18.0.1.0.0.4.dist-info/top_level.txt
odoo_addon_date_range_account-18.0.1.0.0.4.dist-info/RECORD
